roscribe/__init__.py
roscribe/generator.py
roscribe/main.py
roscribe/model.py
roscribe/parser.py
roscribe/prompt.py
roscribe/ros_bs_transformer.py
roscribe/ros_index_chatbot.py
roscribe/ros_index_repo.py
roscribe/ros_index_to_vectorstore.py
roscribe/ui.py
roscribe/visualization.py
roscribe-0.0.4.dist-info/LICENSE
roscribe-0.0.4.dist-info/METADATA
roscribe-0.0.4.dist-info/WHEEL
roscribe-0.0.4.dist-info/entry_points.txt
roscribe-0.0.4.dist-info/top_level.txt
roscribe-0.0.4.dist-info/RECORD
