Metadata-Version: 2.1
Name: roscribe
Version: 0.0.4
Summary: Translate natural language into robot software.
Author-email: RoboCoach Technologies <robocoachtechnologies@gmail.com>
License: MIT License
Project-URL: Homepage, https://github.com/RoboCoachTechnologies/ROScribe
Project-URL: Bug Tracker, https://github.com/RoboCoachTechnologies/ROScribe/issues
Keywords: Large Language Models,AI-assisted Code Generation,Robotics
Classifier: Development Status :: 2 - Pre-Alpha
Classifier: License :: OSI Approved :: MIT License
Classifier: Programming Language :: Python :: 3.8
Classifier: Programming Language :: Python :: 3.9
Classifier: Programming Language :: Python :: 3.10
Classifier: Programming Language :: Python :: 3.11
Classifier: Topic :: Scientific/Engineering :: Artificial Intelligence
Classifier: Topic :: Software Development :: Code Generators 
Classifier: Framework :: Robot Framework :: Tool
Requires-Python: >=3.8
License-File: LICENSE
Requires-Dist: langchain[openai]
Requires-Dist: graphviz
Requires-Dist: schema
Requires-Dist: pysqlite3-binary
Requires-Dist: chromadb
Requires-Dist: tiktoken
Provides-Extra: dev
Requires-Dist: pip-tools ; extra == 'dev'
Requires-Dist: pytest ; extra == 'dev'
